dsbot/__init__.py
dsbot/adapter.py
dsbot/apps.py
dsbot/client.py
dsbot/conf.py
dsbot/decorators.py
dsbot/exceptions.py
dsbot/tasks.py
dsbot/test.py
dsbot/util.py
dsbot/commands/__init__.py
dsbot/commands/default.py
dsbot/management/__init__.py
dsbot/management/commands/__init__.py
dsbot/management/commands/bot.py
dsbot/migrations/__init__.py
django_slack_bot-0.10.1.dist-info/METADATA
django_slack_bot-0.10.1.dist-info/WHEEL
django_slack_bot-0.10.1.dist-info/entry_points.txt
django_slack_bot-0.10.1.dist-info/top_level.txt
django_slack_bot-0.10.1.dist-info/RECORD
