Metadata-Version: 2.1
Name: django_slack_bot
Version: 0.10.1
Summary: Helpers for integrating Slack + Django
Author: Paul Traylor
Classifier: Development Status :: 3 - Alpha
Classifier: Framework :: Django
Classifier: License :: OSI Approved :: MIT License
Classifier: Natural Language :: English
Classifier: Operating System :: OS Independent
Classifier: Programming Language :: Python
Requires-Python: >=3.8
Requires-Dist: aiohttp
Requires-Dist: celery
Requires-Dist: Django >=3.2
Requires-Dist: slack-sdk >=3.5.1
Requires-Dist: importlib-metadata >=1 ; python_version < "3.10"
Provides-Extra: dev
Requires-Dist: ruff ; extra == 'dev'
